cryton/__init__.py
cryton/cli/__init__.py
cryton/cli/cli.py
cryton/cli/commands/__init__.py
cryton/cli/commands/execution_variable.py
cryton/cli/commands/log.py
cryton/cli/commands/plan.py
cryton/cli/commands/plan_template.py
cryton/cli/commands/run.py
cryton/cli/commands/stage.py
cryton/cli/commands/step.py
cryton/cli/commands/worker.py
cryton/cli/config/__init__.py
cryton/cli/config/endpoints.py
cryton/cli/config/settings.py
cryton/cli/entrypoint.py
cryton/cli/utility/__init__.py
cryton/cli/utility/constants.py
cryton/cli/utility/decorators.py
cryton/cli/utility/helpers.py
cryton/hive/__init__.py
cryton/hive/asgi.py
cryton/hive/cli.py
cryton/hive/config/__init__.py
cryton/hive/config/settings.py
cryton/hive/cryton_app/__init__.py
cryton/hive/cryton_app/admin.py
cryton/hive/cryton_app/apps.py
cryton/hive/cryton_app/exceptions.py
cryton/hive/cryton_app/management/__init__.py
cryton/hive/cryton_app/management/commands/__init__.py
cryton/hive/cryton_app/management/commands/start.py
cryton/hive/cryton_app/migrations/0001_initial.py
cryton/hive/cryton_app/migrations/__init__.py
cryton/hive/cryton_app/models.py
cryton/hive/cryton_app/serializers.py
cryton/hive/cryton_app/urls.py
cryton/hive/cryton_app/util.py
cryton/hive/cryton_app/views/__init__.py
cryton/hive/cryton_app/views/execution_variable_views.py
cryton/hive/cryton_app/views/log_views.py
cryton/hive/cryton_app/views/plan_execution_views.py
cryton/hive/cryton_app/views/plan_template_views.py
cryton/hive/cryton_app/views/plan_views.py
cryton/hive/cryton_app/views/run_views.py
cryton/hive/cryton_app/views/stage_execution_views.py
cryton/hive/cryton_app/views/stage_views.py
cryton/hive/cryton_app/views/step_execution_views.py
cryton/hive/cryton_app/views/step_views.py
cryton/hive/cryton_app/views/worker_views.py
cryton/hive/entrypoint.py
cryton/hive/manage.py
cryton/hive/models/__init__.py
cryton/hive/models/abstract.py
cryton/hive/models/plan.py
cryton/hive/models/run.py
cryton/hive/models/stage.py
cryton-3.0.3.dist-info/LICENSE
cryton-3.0.3.dist-info/METADATA
cryton-3.0.3.dist-info/WHEEL
cryton-3.0.3.dist-info/entry_points.txt
cryton-3.0.3.dist-info/RECORD
